flasket/api/x-gitlab.yml
flasket/clients/gitlab.py
flasket_gitlab-0.2.0.dist-info/LICENSE
flasket_gitlab-0.2.0.dist-info/METADATA
flasket_gitlab-0.2.0.dist-info/WHEEL
flasket_gitlab-0.2.0.dist-info/top_level.txt
flasket_gitlab-0.2.0.dist-info/zip-safe
flasket_gitlab-0.2.0.dist-info/RECORD
