Metadata-Version: 2.1
Name: flasket-gitlab
Version: 0.2.0
Summary: A flasket plugin.
Author-email: Julien Lecomte <julien@lecomte.at>
License: MIT
Project-URL: Homepage, https://gitlab.com/jlecomte/python/flasket-gitlab
Project-URL: Documentation, https://jlecomte.gitlab.io/python/flasket_gitlab/
Project-URL: Source code, https://gitlab.com/jlecomte/python/flasket-gitlab
Project-URL: Bug tracker, https://gitlab.com/jlecomte/python/flasket-gitlab/-/issues
Classifier: License :: OSI Approved :: MIT License
Classifier: Intended Audience :: Developers
Classifier: Development Status :: 3 - Alpha
Classifier: Programming Language :: Python :: 3 :: Only
Classifier: Programming Language :: Python :: 3.7
Classifier: Programming Language :: Python :: 3.8
Classifier: Programming Language :: Python :: 3.9
Requires-Python: >=3.7
License-File: LICENSE
Requires-Dist: flasket (>0.12.1)
Requires-Dist: python-gitlab
